LICENSE
MANIFEST.in
README.md
requirements.txt
setup.py
cluster_vcf_records/__init__.py
cluster_vcf_records/allele_combinations.py
cluster_vcf_records/utils.py
cluster_vcf_records/variant_tracking.py
cluster_vcf_records/vcf_clusterer.py
cluster_vcf_records/vcf_file_read.py
cluster_vcf_records/vcf_merge.py
cluster_vcf_records/vcf_record.py
cluster_vcf_records/vcf_record_cluster.py
cluster_vcf_records.egg-info/PKG-INFO
cluster_vcf_records.egg-info/SOURCES.txt
cluster_vcf_records.egg-info/dependency_links.txt
cluster_vcf_records.egg-info/requires.txt
cluster_vcf_records.egg-info/top_level.txt
tests/__init__.py
tests/test_allele_combinations.py
tests/test_utils.py
tests/test_variant_tracking.py
tests/test_vcf_clusterer.py
tests/test_vcf_file_read.py
tests/test_vcf_merge.py
tests/test_vcf_record.py
tests/test_vcf_record_cluster.py