Metadata-Version: 1.1
Name: cluster-vcf-records
Version: 0.13.3
Summary: Package to cluster VCF records. For use by gramtools and minos
Home-page: https://github.com/iqbal-lab-org/cluster_vcf_records
Author: Martin Hunt
Author-email: mhunt@ebi.ac.uk
License: MIT
Platform: UNKNOWN
Classifier: Development Status :: 4 - Beta
Classifier: Topic :: Scientific/Engineering :: Bio-Informatics
Classifier: Programming Language :: Python :: 3 :: Only
Classifier: License :: OSI Approved :: MIT License
